{
  "$schema": "https://developer.microsoft.com/json-schemas/fabric/item/report/definition/visualContainer/2.9.0/schema.json",
  "name": "65ed3bd583e6391cd23c",
  "position": {
    "x": 725.53885973110937,
    "y": 74.541663671004386,
    "z": 7000,
    "height": 303.13609892875115,
    "width": 533.38701560140919,
    "tabOrder": 7000
  },
  "visual": {
    "visualType": "lineChart",
    "query": {
      "queryState": {
        "Category": {
          "projections": [
            {
              "field": {
                "Column": {
                  "Expression": {
                    "SourceRef": {
                      "Entity": "DimDate"
                    }
                  },
                  "Property": "MonthName"
                }
              },
              "queryRef": "DimDate.MonthName",
              "nativeQueryRef": "MonthName",
              "active": true
            }
          ]
        },
        "Y": {
          "projections": [
            {
              "field": {
                "Measure": {
                  "Expression": {
                    "SourceRef": {
                      "Entity": "_Measures"
                    }
                  },
                  "Property": "Total Txn Value"
                }
              },
              "queryRef": "_Measures.Total Txn Value",
              "nativeQueryRef": "Total Txn Value"
            }
          ]
        }
      }
    },
    "objects": {
      "legend": [
        {
          "properties": {
            "show": {
              "expr": {
                "Literal": {
                  "Value": "false"
                }
              }
            }
          }
        }
      ],
      "categoryAxis": [
        {
          "properties": {
            "maxMarginFactor": {
              "expr": {
                "Literal": {
                  "Value": "20L"
                }
              }
            },
            "concatenateLabels": {
              "expr": {
                "Literal": {
                  "Value": "false"
                }
              }
            },
            "fontFamily": {
              "expr": {
                "Literal": {
                  "Value": "'''Cambria Math'''"
                }
              }
            },
            "fontSize": {
              "expr": {
                "Literal": {
                  "Value": "8D"
                }
              }
            },
            "bold": {
              "expr": {
                "Literal": {
                  "Value": "true"
                }
              }
            },
            "labelColor": {
              "solid": {
                "color": {
                  "expr": {
                    "ThemeDataColor": {
                      "ColorId": 7,
                      "Percent": -0.5
                    }
                  }
                }
              }
            },
            "showAxisTitle": {
              "expr": {
                "Literal": {
                  "Value": "false"
                }
              }
            }
          }
        }
      ],
      "valueAxis": [
        {
          "properties": {
            "fontFamily": {
              "expr": {
                "Literal": {
                  "Value": "'''Cambria Math'''"
                }
              }
            },
            "fontSize": {
              "expr": {
                "Literal": {
                  "Value": "12D"
                }
              }
            },
            "bold": {
              "expr": {
                "Literal": {
                  "Value": "true"
                }
              }
            },
            "showAxisTitle": {
              "expr": {
                "Literal": {
                  "Value": "true"
                }
              }
            },
            "titleFontFamily": {
              "expr": {
                "Literal": {
                  "Value": "'''Cambria Math'''"
                }
              }
            },
            "titleFontSize": {
              "expr": {
                "Literal": {
                  "Value": "10D"
                }
              }
            },
            "titleBold": {
              "expr": {
                "Literal": {
                  "Value": "true"
                }
              }
            },
            "gridlineShow": {
              "expr": {
                "Literal": {
                  "Value": "false"
                }
              }
            },
            "labelDisplayUnits": {
              "expr": {
                "Literal": {
                  "Value": "1000000000D"
                }
              }
            }
          }
        }
      ],
      "zoom": [
        {
          "properties": {
            "show": {
              "expr": {
                "Literal": {
                  "Value": "false"
                }
              }
            },
            "showOnValueAxis": {
              "expr": {
                "Literal": {
                  "Value": "false"
                }
              }
            },
            "showLabels": {
              "expr": {
                "Literal": {
                  "Value": "false"
                }
              }
            },
            "showTooltip": {
              "expr": {
                "Literal": {
                  "Value": "false"
                }
              }
            },
            "showOnValueSecAxis": {
              "expr": {
                "Literal": {
                  "Value": "false"
                }
              }
            }
          }
        }
      ],
      "dataPoint": [
        {
          "properties": {
            "fill": {
              "solid": {
                "color": {
                  "expr": {
                    "ThemeDataColor": {
                      "ColorId": 7,
                      "Percent": -0.5
                    }
                  }
                }
              }
            }
          },
          "selector": {
            "metadata": "_Measures.Txn YoY%"
          }
        },
        {
          "properties": {
            "fill": {
              "solid": {
                "color": {
                  "expr": {
                    "ThemeDataColor": {
                      "ColorId": 3,
                      "Percent": 0.2
                    }
                  }
                }
              }
            }
          }
        }
      ],
      "labels": [
        {
          "properties": {
            "show": {
              "expr": {
                "Literal": {
                  "Value": "false"
                }
              }
            }
          }
        }
      ],
      "lineStyles": [
        {
          "properties": {
            "strokeWidth": {
              "expr": {
                "Literal": {
                  "Value": "3D"
                }
              }
            },
            "showMarker": {
              "expr": {
                "Literal": {
                  "Value": "true"
                }
              }
            },
            "markerShape": {
              "expr": {
                "Literal": {
                  "Value": "'diamond'"
                }
              }
            },
            "markerColor": {
              "solid": {
                "color": {
                  "expr": {
                    "ThemeDataColor": {
                      "ColorId": 0,
                      "Percent": 0
                    }
                  }
                }
              }
            },
            "lineChartType": {
              "expr": {
                "Literal": {
                  "Value": "'linear'"
                }
              }
            },
            "areaShow": {
              "expr": {
                "Literal": {
                  "Value": "true"
                }
              }
            }
          }
        }
      ],
      "markers": [
        {
          "properties": {
            "borderShow": {
              "expr": {
                "Literal": {
                  "Value": "true"
                }
              }
            }
          }
        }
      ],
      "y2Axis": [
        {
          "properties": {
            "secLabelDisplayUnits": {
              "expr": {
                "Literal": {
                  "Value": "1000000000D"
                }
              }
            }
          }
        }
      ]
    },
    "visualContainerObjects": {
      "title": [
        {
          "properties": {
            "titleWrap": {
              "expr": {
                "Literal": {
                  "Value": "true"
                }
              }
            },
            "fontColor": {
              "solid": {
                "color": {
                  "expr": {
                    "ThemeDataColor": {
                      "ColorId": 0,
                      "Percent": -0.6
                    }
                  }
                }
              }
            },
            "alignment": {
              "expr": {
                "Literal": {
                  "Value": "'center'"
                }
              }
            },
            "fontSize": {
              "expr": {
                "Literal": {
                  "Value": "16D"
                }
              }
            },
            "bold": {
              "expr": {
                "Literal": {
                  "Value": "true"
                }
              }
            },
            "fontFamily": {
              "expr": {
                "Literal": {
                  "Value": "'Constantia'"
                }
              }
            },
            "text": {
              "expr": {
                "Literal": {
                  "Value": "'Total Txn  by Month'"
                }
              }
            }
          }
        }
      ],
      "background": [
        {
          "properties": {
            "show": {
              "expr": {
                "Literal": {
                  "Value": "true"
                }
              }
            },
            "transparency": {
              "expr": {
                "Literal": {
                  "Value": "0D"
                }
              }
            }
          }
        }
      ],
      "border": [
        {
          "properties": {
            "show": {
              "expr": {
                "Literal": {
                  "Value": "true"
                }
              }
            },
            "color": {
              "solid": {
                "color": {
                  "expr": {
                    "ThemeDataColor": {
                      "ColorId": 9,
                      "Percent": 0
                    }
                  }
                }
              }
            },
            "radius": {
              "expr": {
                "Literal": {
                  "Value": "6D"
                }
              }
            },
            "width": {
              "expr": {
                "Literal": {
                  "Value": "1D"
                }
              }
            }
          }
        }
      ]
    },
    "drillFilterOtherVisuals": true
  }
}